setup.py
PyRockPaperScissorsGame/RockPaperScissorsGame.py
PyRockPaperScissorsGame/__init__.py
PyRockPaperScissorsGame.egg-info/PKG-INFO
PyRockPaperScissorsGame.egg-info/SOURCES.txt
PyRockPaperScissorsGame.egg-info/dependency_links.txt
PyRockPaperScissorsGame.egg-info/top_level.txt