Metadata-Version: 2.1
Name: PyRockPaperScissorsGame
Version: 0.0.3
Summary: A quick rock paper scissors game
Home-page: https://github.com/NeShkApp/RockPaperScissors
Author: NeShk
Author-email: <bodia.nazar4669@gmail.com>
License: UNKNOWN
Keywords: python,game,function,rps,rock,paper,scissors
Platform: UNKNOWN
Classifier: Development Status :: 1 - Planning
Classifier: Intended Audience :: Developers
Classifier: Operating System :: Unix
Classifier: Operating System :: MacOS :: MacOS X
Classifier: Operating System :: Microsoft :: Windows
